{
  "place": "東京",
  "date": "20260517",
  "source": "realtime",
  "generated_at": "2026-05-17T09:27:22",
  "total_races": 12,
  "surfaces": {
    "芝": {
      "race_count": 6,
      "frame_bias": [
        {
          "内外": "内",
          "勝率": 0.057,
          "複勝率": 0.171,
          "出走数": 35
        },
        {
          "内外": "外",
          "勝率": 0.087,
          "複勝率": 0.261,
          "出走数": 46
        }
      ],
      "style_bias": [
        {
          "脚質": "逃げ先行",
          "勝率": 0.094,
          "複勝率": 0.312,
          "出走数": 32
        },
        {
          "脚質": "差し追込",
          "勝率": 0.028,
          "複勝率": 0.111,
          "出走数": 36
        }
      ],
      "best_combo": {
        "内外": "外",
        "脚質": "逃げ先行",
        "複勝率": 0.294,
        "出走数": 17
      },
      "combo_matrix": [
        {
          "内外": "内",
          "脚質": "差し追込",
          "複勝率": 0.0,
          "出走数": 16
        },
        {
          "内外": "内",
          "脚質": "逃げ先行",
          "複勝率": 0.333,
          "出走数": 15
        },
        {
          "内外": "外",
          "脚質": "差し追込",
          "複勝率": 0.2,
          "出走数": 20
        },
        {
          "内外": "外",
          "脚質": "逃げ先行",
          "複勝率": 0.294,
          "出走数": 17
        }
      ]
    },
    "ダート": {
      "race_count": 6,
      "frame_bias": [
        {
          "内外": "内",
          "勝率": 0.103,
          "複勝率": 0.231,
          "出走数": 39
        },
        {
          "内外": "外",
          "勝率": 0.045,
          "複勝率": 0.205,
          "出走数": 44
        }
      ],
      "style_bias": [
        {
          "脚質": "逃げ先行",
          "勝率": 0.143,
          "複勝率": 0.321,
          "出走数": 28
        },
        {
          "脚質": "差し追込",
          "勝率": 0.045,
          "複勝率": 0.182,
          "出走数": 44
        }
      ],
      "best_combo": {
        "内外": "内",
        "脚質": "逃げ先行",
        "複勝率": 0.286,
        "出走数": 14
      },
      "combo_matrix": [
        {
          "内外": "内",
          "脚質": "差し追込",
          "複勝率": 0.211,
          "出走数": 19
        },
        {
          "内外": "内",
          "脚質": "逃げ先行",
          "複勝率": 0.286,
          "出走数": 14
        },
        {
          "内外": "外",
          "脚質": "差し追込",
          "複勝率": 0.16,
          "出走数": 25
        },
        {
          "内外": "外",
          "脚質": "逃げ先行",
          "複勝率": 0.357,
          "出走数": 14
        }
      ]
    }
  },
  "hot_jockeys": [
    {
      "騎手": "丹内",
      "最大人気差": 9.0,
      "騎乗数": 9,
      "勝利": 1,
      "複勝": 2
    },
    {
      "騎手": "江田照",
      "最大人気差": 9.0,
      "騎乗数": 5,
      "勝利": 0,
      "複勝": 1
    },
    {
      "騎手": "小林脩",
      "最大人気差": 8.0,
      "騎乗数": 6,
      "勝利": 0,
      "複勝": 1
    },
    {
      "騎手": "松若",
      "最大人気差": 7.0,
      "騎乗数": 2,
      "勝利": 0,
      "複勝": 1
    },
    {
      "騎手": "原田和",
      "最大人気差": 6.0,
      "騎乗数": 4,
      "勝利": 0,
      "複勝": 1
    },
    {
      "騎手": "岩田望",
      "最大人気差": 5.0,
      "騎乗数": 9,
      "勝利": 2,
      "複勝": 2
    }
  ],
  "races": [
    {
      "R": 1,
      "surface": "ダート",
      "top3": [
        {
          "着順": 1,
          "馬番": 2,
          "内外": "内",
          "脚質": "逃げ先行",
          "騎手": "北村宏"
        },
        {
          "着順": 2,
          "馬番": 13,
          "内外": "外",
          "脚質": "逃げ先行",
          "騎手": "ディー"
        },
        {
          "着順": 3,
          "馬番": 4,
          "内外": "内",
          "脚質": "差し追込",
          "騎手": "ゴンサ"
        }
      ]
    },
    {
      "R": 2,
      "surface": "ダート",
      "top3": [
        {
          "着順": 1,
          "馬番": 14,
          "内外": "外",
          "脚質": "逃げ先行",
          "騎手": "田辺"
        },
        {
          "着順": 2,
          "馬番": 5,
          "内外": "内",
          "脚質": "逃げ先行",
          "騎手": "北村宏"
        },
        {
          "着順": 3,
          "馬番": 4,
          "内外": "内",
          "脚質": "差し追込",
          "騎手": "小林脩"
        }
      ]
    },
    {
      "R": 3,
      "surface": "ダート",
      "top3": [
        {
          "着順": 1,
          "馬番": 4,
          "内外": "内",
          "脚質": "差し追込",
          "騎手": "岩田望"
        },
        {
          "着順": 2,
          "馬番": 2,
          "内外": "内",
          "脚質": "逃げ先行",
          "騎手": "大野"
        },
        {
          "着順": 3,
          "馬番": 9,
          "内外": "外",
          "脚質": "差し追込",
          "騎手": "菅原明"
        }
      ]
    },
    {
      "R": 4,
      "surface": "芝",
      "top3": [
        {
          "着順": 1,
          "馬番": 16,
          "内外": "外",
          "脚質": "差し追込",
          "騎手": "レーン"
        },
        {
          "着順": 2,
          "馬番": 4,
          "内外": "内",
          "脚質": "逃げ先行",
          "騎手": "横山武"
        },
        {
          "着順": 3,
          "馬番": 9,
          "内外": "外",
          "脚質": "差し追込",
          "騎手": "ゴンサ"
        }
      ]
    },
    {
      "R": 5,
      "surface": "芝",
      "top3": [
        {
          "着順": 1,
          "馬番": 5,
          "内外": "外",
          "脚質": "逃げ先行",
          "騎手": "津村"
        },
        {
          "着順": 2,
          "馬番": 6,
          "内外": "外",
          "脚質": "差し追込",
          "騎手": "江田照"
        },
        {
          "着順": 3,
          "馬番": 11,
          "内外": "外",
          "脚質": null,
          "騎手": "ルメー"
        }
      ]
    },
    {
      "R": 6,
      "surface": "ダート",
      "top3": [
        {
          "着順": 1,
          "馬番": 6,
          "内外": "外",
          "脚質": "逃げ先行",
          "騎手": "レーン"
        },
        {
          "着順": 2,
          "馬番": 1,
          "内外": "内",
          "脚質": null,
          "騎手": "横山武"
        },
        {
          "着順": 3,
          "馬番": 7,
          "内外": "外",
          "脚質": "差し追込",
          "騎手": "長岡"
        }
      ]
    },
    {
      "R": 7,
      "surface": "芝",
      "top3": [
        {
          "着順": 1,
          "馬番": 2,
          "内外": "内",
          "脚質": null,
          "騎手": "坂井"
        },
        {
          "着順": 2,
          "馬番": 5,
          "内外": "外",
          "脚質": null,
          "騎手": "北村宏"
        },
        {
          "着順": 3,
          "馬番": 6,
          "内外": "外",
          "脚質": "逃げ先行",
          "騎手": "戸崎圭"
        }
      ]
    },
    {
      "R": 8,
      "surface": "芝",
      "top3": [
        {
          "着順": 1,
          "馬番": 5,
          "内外": "内",
          "脚質": "逃げ先行",
          "騎手": "丹内"
        },
        {
          "着順": 2,
          "馬番": 8,
          "内外": "外",
          "脚質": "逃げ先行",
          "騎手": "レーン"
        },
        {
          "着順": 3,
          "馬番": 11,
          "内外": "外",
          "脚質": "差し追込",
          "騎手": "原田和"
        }
      ]
    },
    {
      "R": 9,
      "surface": "芝",
      "top3": [
        {
          "着順": 1,
          "馬番": 12,
          "内外": "外",
          "脚質": null,
          "騎手": "ゴンサ"
        },
        {
          "着順": 2,
          "馬番": 1,
          "内外": "内",
          "脚質": "逃げ先行",
          "騎手": "菅原明"
        },
        {
          "着順": 3,
          "馬番": 7,
          "内外": "外",
          "脚質": "逃げ先行",
          "騎手": "丹内"
        }
      ]
    },
    {
      "R": 10,
      "surface": "ダート",
      "top3": [
        {
          "着順": 1,
          "馬番": 7,
          "内外": "内",
          "脚質": "逃げ先行",
          "騎手": "岩田望"
        },
        {
          "着順": 2,
          "馬番": 13,
          "内外": "外",
          "脚質": "逃げ先行",
          "騎手": "ゴンサ"
        },
        {
          "着順": 3,
          "馬番": 8,
          "内外": "外",
          "脚質": "差し追込",
          "騎手": "松若"
        }
      ]
    },
    {
      "R": 11,
      "surface": "芝",
      "top3": [
        {
          "着順": 1,
          "馬番": 12,
          "内外": "外",
          "脚質": "逃げ先行",
          "騎手": "ルメー"
        },
        {
          "着順": 2,
          "馬番": 8,
          "内外": "内",
          "脚質": "逃げ先行",
          "騎手": "川田"
        },
        {
          "着順": 3,
          "馬番": 7,
          "内外": "内",
          "脚質": "逃げ先行",
          "騎手": "西村淳"
        }
      ]
    },
    {
      "R": 12,
      "surface": "ダート",
      "top3": [
        {
          "着順": 1,
          "馬番": 8,
          "内外": "内",
          "脚質": "差し追込",
          "騎手": "ルメー"
        },
        {
          "着順": 2,
          "馬番": 11,
          "内外": "外",
          "脚質": "逃げ先行",
          "騎手": "レーン"
        },
        {
          "着順": 3,
          "馬番": 12,
          "内外": "外",
          "脚質": "差し追込",
          "騎手": "松山"
        }
      ]
    }
  ]
}